simplify_vcd/changes.py
simplify_vcd/changes_test.py
simplify_vcd/simplify.py
simplify_vcd/time.py
simplify_vcd/time_test.py
simplify_vcd/vcd_file.py
simplify_vcd/vcd_file_test.py
simplify_vcd-1.0.0.dist-info/METADATA
simplify_vcd-1.0.0.dist-info/WHEEL
simplify_vcd-1.0.0.dist-info/entry_points.txt
simplify_vcd-1.0.0.dist-info/licenses/LICENSE.md
simplify_vcd-1.0.0.dist-info/RECORD
