Metadata-Version: 2.4
Name: simplify-vcd
Version: 1.0.0
Summary: Clip, trim and reduce VCD files
Project-URL: Homepage, https://codeberg.org/MikeCoats/simplify-vcd
Project-URL: Repository, https://codeberg.org/MikeCoats/simplify-vcd.git
Project-URL: Issues, https://codeberg.org/MikeCoats/simplify-vcd/issues
Author-email: Mike Coats <i.am@mikecoats.com>
License-Expression: GPL-3.0-or-later
License-File: LICENSE.md
Keywords: checking,connectivity,design,drawing,eda,electronics,logic,simulation,verification,vhdl
Classifier: Development Status :: 5 - Production/Stable
Classifier: Environment :: Console
Classifier: Framework :: Pytest
Classifier: Intended Audience :: Developers
Classifier: Intended Audience :: End Users/Desktop
Classifier: Intended Audience :: Manufacturing
Classifier: Intended Audience :: Science/Research
Classifier: License :: OSI Approved :: GNU General Public License v3 or later (GPLv3+)
Classifier: Natural Language :: English
Classifier: Operating System :: OS Independent
Classifier: Programming Language :: Python :: 3
Classifier: Programming Language :: Python :: 3.11
Classifier: Topic :: Scientific/Engineering
Classifier: Topic :: Scientific/Engineering :: Electronic Design Automation (EDA)
Classifier: Topic :: Scientific/Engineering :: Information Analysis
Classifier: Topic :: Scientific/Engineering :: Visualization
Classifier: Topic :: Software Development :: Embedded Systems
Requires-Python: >=3.11
Requires-Dist: click~=8.1.8
Provides-Extra: dev
Requires-Dist: black~=24.10.0; extra == 'dev'
Requires-Dist: build~=1.2.2; extra == 'dev'
Requires-Dist: coverage~=7.6.12; extra == 'dev'
Requires-Dist: flake8-pyproject~=1.2.3; extra == 'dev'
Requires-Dist: flake8~=7.1.1; extra == 'dev'
Requires-Dist: isort~=5.13.2; extra == 'dev'
Requires-Dist: pylint~=3.3.3; extra == 'dev'
Requires-Dist: pytest~=8.3.4; extra == 'dev'
Requires-Dist: twine~=6.1.0; extra == 'dev'
